{
    "os": "Linux-3.10.0-957.12.2.el7.x86_64-x86_64-with-glibc2.17",
    "python": "3.8.12",
    "heartbeatAt": "2022-03-29T13:42:45.640954",
    "startedAt": "2022-03-29T13:42:44.441088",
    "docker": null,
    "gpu": "Quadro RTX 6000",
    "gpu_count": 1,
    "cpu_count": 80,
    "cuda": "10.0.130",
    "args": [
        "-f",
        "/lila/home/harrigan/.local/share/jupyter/runtime/kernel-a18f601a-a1c7-4c17-aa55-06c64bc28d99.json"
    ],
    "state": "running",
    "program": "docs/examples/wandb-jvsc-a7cc7f1d-6ead-4b9e-ba57-327671a8524d.ipynb",
    "root": "/lila/home/harrigan/damuta",
    "git": {
        "remote": "https://github.com/morrislab/damuta",
        "commit": "dd2e24a404acccdba6b8676af0d0814b2c0a8843"
    },
    "email": "cait.harrigan@mail.utoronto.ca",
    "host": "glass",
    "username": "harrigan",
    "executable": "/home/harrigan/miniconda3/envs/pymc3/bin/python"
}
